[
    {
        "round": 1,
        "mae": 26.46874008178711
    },
    {
        "round": 2,
        "mae": 3.1281558990478517
    },
    {
        "round": 3,
        "mae": 2.885851287841797
    },
    {
        "round": 4,
        "mae": 2.857953596115112
    },
    {
        "round": 5,
        "mae": 2.8623498916625976
    },
    {
        "round": 6,
        "mae": 2.8696228504180907
    },
    {
        "round": 7,
        "mae": 2.821785640716553
    },
    {
        "round": 8,
        "mae": 2.815676546096802
    },
    {
        "round": 9,
        "mae": 2.8390798568725586
    },
    {
        "round": 10,
        "mae": 2.872080993652344
    },
    {
        "round": 11,
        "mae": 2.8186583518981934
    },
    {
        "round": 12,
        "mae": 2.941412591934204
    },
    {
        "round": 13,
        "mae": 2.7999363422393797
    },
    {
        "round": 14,
        "mae": 2.907409906387329
    },
    {
        "round": 15,
        "mae": 3.0728151321411135
    },
    {
        "round": 16,
        "mae": 2.807933235168457
    },
    {
        "round": 17,
        "mae": 2.8690131187438963
    },
    {
        "round": 18,
        "mae": 2.850091648101807
    },
    {
        "round": 19,
        "mae": 2.8071639060974123
    },
    {
        "round": 20,
        "mae": 3.001698303222656
    }
]